fluentwidgets/__init__.py
fluentwidgets/_rc/__init__.py
fluentwidgets/_rc/resource.py
fluentwidgets/common/__init__.py
fluentwidgets/common/animation.py
fluentwidgets/common/auto_wrap.py
fluentwidgets/common/color.py
fluentwidgets/common/config.py
fluentwidgets/common/exception_handler.py
fluentwidgets/common/font.py
fluentwidgets/common/icon.py
fluentwidgets/common/image_utils.py
fluentwidgets/common/overload.py
fluentwidgets/common/router.py
fluentwidgets/common/screen.py
fluentwidgets/common/smooth_scroll.py
fluentwidgets/common/style_sheet.py
fluentwidgets/common/theme_listener.py
fluentwidgets/common/translator.py
fluentwidgets/components/__init__.py
fluentwidgets/components/date_time/__init__.py
fluentwidgets/components/date_time/calendar_picker.py
fluentwidgets/components/date_time/calendar_view.py
fluentwidgets/components/date_time/date_picker.py
fluentwidgets/components/date_time/fast_calendar_view.py
fluentwidgets/components/date_time/picker_base.py
fluentwidgets/components/date_time/time_picker.py
fluentwidgets/components/dialog_box/__init__.py
fluentwidgets/components/dialog_box/color_dialog.py
fluentwidgets/components/dialog_box/dialog.py
fluentwidgets/components/dialog_box/folder_list_dialog.py
fluentwidgets/components/dialog_box/mask_dialog_base.py
fluentwidgets/components/dialog_box/message_box_base.py
fluentwidgets/components/dialog_box/message_dialog.py
fluentwidgets/components/layout/__init__.py
fluentwidgets/components/layout/expand_layout.py
fluentwidgets/components/layout/flow_layout.py
fluentwidgets/components/layout/v_box_layout.py
fluentwidgets/components/material/__init__.py
fluentwidgets/components/material/acrylic_combo_box.py
fluentwidgets/components/material/acrylic_flyout.py
fluentwidgets/components/material/acrylic_line_edit.py
fluentwidgets/components/material/acrylic_menu.py
fluentwidgets/components/material/acrylic_tool_tip.py
fluentwidgets/components/material/acrylic_widget.py
fluentwidgets/components/navigation/__init__.py
fhfluentwidgets-0.1.2.dist-info/METADATA
fhfluentwidgets-0.1.2.dist-info/WHEEL
fhfluentwidgets-0.1.2.dist-info/RECORD
