Metadata-Version: 2.1
Name: fhfluentwidgets
Version: 0.1.2
Summary: A fluent design widgets library based on PySide2
Author: wsd
Author-email: wsd@fhit.cn
Requires-Python: >=3.8,<4.0
Classifier: Programming Language :: Python :: 3
Classifier: Programming Language :: Python :: 3.8
Classifier: Programming Language :: Python :: 3.9
Classifier: Programming Language :: Python :: 3.10
Classifier: Programming Language :: Python :: 3.11
Classifier: Programming Language :: Python :: 3.12
Classifier: Programming Language :: Python :: 3.13
